{
    "root": {
        "title": "Расписание группы P3115",
        "schedule": {
            "day": {
                "short-name-of-day": "Чт",
                "lessons": {
                    "lesson": [
                        {
                            "week": "3, 5, 7, 9, 11, 13, 15, 17",
                            "time": "10:00-11:30",
                            "place": "Кронверкский пр., д.49, лит.А",
                            "room": "369А ауд.",
                            "name": "Дискретная математика (прак)",
                            "teacher": "Поляков Владимир Иванович",
                            "lesson-format": "Очно - дистанционный"
                        },
                        {
                            "week": "3, 5, 7, 9, 11, 13, 15, 17",
                            "time": "11:40-13:10",
                            "place": "Кронверкский пр., д.49, лит.А",
                            "room": "369А ауд.",
                            "name": "Дискретная математика (прак)",
                            "teacher": "Поляков Владимир Иванович",
                            "lesson-format": "Очно - дистанционный"
                        },
                        {
                            "week": "3, 5, 7, 9, 11, 13, 15, 17",
                            "time": "13:30-15:00",
                            "place": "Кронверкский пр., д.49, лит.А",
                            "room": "285 ауд.",
                            "name": "Дискретная математика (лек)",
                            "teacher": "Поляков Владимир Иванович",
                            "lesson-format": "Очно - дистанционный"
                        }
                    ]
                }
            }
        }
    }
}
